Bromo/__init__.py
Bromo/bromo.py
bromo-0.2.dist-info/LICENSE
bromo-0.2.dist-info/METADATA
bromo-0.2.dist-info/WHEEL
bromo-0.2.dist-info/top_level.txt
bromo-0.2.dist-info/RECORD
